{
  "uuid": "07a410d9-6b3d-4e3b-942d-127d3525c4d1",
  "title": "Helper Method Contract",
  "description": "Created using the helper method",
  "participants": [
    "uuid-participant-1",
    "uuid-participant-2",
    "d66af83c-5742-419a-ac7c-1aa4b9647927"
  ],
  "steps": [
    {
      "id": "step-1",
      "description": "Step one description",
      "magic_spell": null,
      "order": 0,
      "signatures": {
        "uuid-participant-1": null,
        "uuid-participant-2": null,
        "d66af83c-5742-419a-ac7c-1aa4b9647927": null
      },
      "completed": false,
      "created_at": "1754011196870"
    },
    {
      "id": "step-2",
      "description": "Step two description",
      "magic_spell": null,
      "order": 1,
      "signatures": {
        "uuid-participant-1": null,
        "uuid-participant-2": null,
        "d66af83c-5742-419a-ac7c-1aa4b9647927": null
      },
      "completed": false,
      "created_at": "1754011196870"
    },
    {
      "id": "step-3",
      "description": "Final step description",
      "magic_spell": null,
      "order": 2,
      "signatures": {
        "uuid-participant-1": null,
        "uuid-participant-2": null,
        "d66af83c-5742-419a-ac7c-1aa4b9647927": null
      },
      "completed": false,
      "created_at": "1754011196870"
    }
  ],
  "product_uuid": null,
  "bdo_location": null,
  "created_at": "1754011196870",
  "updated_at": "1754011196870",
  "status": "active",
  "creator": "d66af83c-5742-419a-ac7c-1aa4b9647927"
}